djangocms_nbrender/__init__.py
djangocms_nbrender/admin.py
djangocms_nbrender/apps.py
djangocms_nbrender/cms_app.py
djangocms_nbrender/cms_apps.py
djangocms_nbrender/cms_plugins.py
djangocms_nbrender/models.py
djangocms_nbrender/tests.py
djangocms_nbrender/urls.py
djangocms_nbrender/utils.py
djangocms_nbrender/views.py
djangocms_nbrender/migrations/0001_initial.py
djangocms_nbrender/migrations/0002_notebook_web.py
djangocms_nbrender/migrations/__init__.py
djangocms_nbrender/static/.DS_Store
djangocms_nbrender/static/djangocms_nbrender/.DS_Store
djangocms_nbrender/static/djangocms_nbrender/css/notebook.css
djangocms_nbrender/templates/.DS_Store
djangocms_nbrender/templates/djangocms_nbrender/notebook_detail.html
djangocms_nbrender/templates/djangocms_nbrender/plugins/notebookviewer.html
djangocms_nbrender-0.0.6.dist-info/DESCRIPTION.rst
djangocms_nbrender-0.0.6.dist-info/METADATA
djangocms_nbrender-0.0.6.dist-info/RECORD
djangocms_nbrender-0.0.6.dist-info/WHEEL
djangocms_nbrender-0.0.6.dist-info/metadata.json
djangocms_nbrender-0.0.6.dist-info/pbr.json
djangocms_nbrender-0.0.6.dist-info/top_level.txt
