Metadata-Version: 2.0
Name: djangocms-nbrender
Version: 0.0.6
Summary: Render notebook in Django
Home-page: https://github.com/correctiv/djangocms-nbrender
Author: Stefan Wehrmeyer
Author-email: stefan.wehrmeyer@correctiv.org
License: MIT
Platform: UNKNOWN
Classifier: Development Status :: 5 - Production/Stable
Classifier: Environment :: Web Environment
Classifier: Framework :: Django
Classifier: Intended Audience :: Developers
Classifier: License :: OSI Approved :: MIT License
Classifier: Natural Language :: English
Classifier: Operating System :: OS Independent
Classifier: Programming Language :: Python :: 2.7
Classifier: Programming Language :: Python :: 3.5
Classifier: Topic :: Internet :: WWW/HTTP
Requires-Dist: Django
Requires-Dist: django-cms
Requires-Dist: ipython
Requires-Dist: nbconvert[execute]
